pytiip/__init__.py
pytiip/tiip.py
pytiip-3.0.2.dist-info/LICENSE.txt
pytiip-3.0.2.dist-info/METADATA
pytiip-3.0.2.dist-info/RECORD
pytiip-3.0.2.dist-info/WHEEL
pytiip-3.0.2.dist-info/top_level.txt
