Metadata-Version: 2.1
Name: pytiip
Version: 3.0.2
Summary: TIIP-protocol implementation for Python
Home-page: https://github.com/MickMack1983/pytiip.git
Author: Esbjorn Blomquist, Jesper Ahlberg, Mikael Magnusson
Author-email: mikael.m.magnusson@gmail.com
License: MIT License
Keywords: Industrial Internet Things Protocol
Platform: UNKNOWN
Classifier: Development Status :: 5 - Production/Stable
Classifier: Intended Audience :: Developers
Classifier: Natural Language :: English
Classifier: License :: OSI Approved :: MIT License
Classifier: Programming Language :: Python
Classifier: Programming Language :: Python :: 2
Classifier: Programming Language :: Python :: 2.6
Classifier: Programming Language :: Python :: 2.7
Classifier: Programming Language :: Python :: 3
Classifier: Programming Language :: Python :: 3.5
Classifier: Programming Language :: Python :: 3.6
Classifier: Programming Language :: Python :: 3.7
Requires-Dist: python-dateutil
